Workbook

Sheet Sales_Data
A1: Order_ID | B1: Date | C1: Customer | D1: Product_ID | E1: Quantity | F1: Unit_Price | G1: Region | H1: Total Revenue per order | I1: Total revenue for all sales | J1: Region | K1: Total Revenue Per Region | L1: Contribution Percentage Of Each Region From Total Revenue | M1: Product_Name_By_VLOOKUP | N1: Product_Name_By_XLOOKUP | O1: Cost_Price_By_VLOOKUP | P1: Cost_Price_By_XLOOKUP | Q1: Profit Per Order | R1: Category_By_VLOOKUP | S1: Category_By_XLOOKUP | T1: Order Classification By Revenue
A2: 1010 | B2: 2025-01-25 | C2: Shira | D2: P105 | E2: 5 | F2: 300 | G2: South | H2: =E2*F2 -> 1500 | I2: =SUM(H2:H11) -> 5210 | J2: North | K2: =SUMIF($G:$G,J2,$H:$H) -> 1360 | L2: =B17/SUM($B$17:$B$20) -> 0.17274472 | M2: =VLOOKUP(D2,Products_Data!$A:$D,2,FALSE) -> Smartphone | N2: =_xlfn.XLOOKUP(D2,Products_Data!$A:$A,Products_Data!$B:$B) -> Smartphone | O2: =VLOOKUP(D2,Products_Data!$A:$D,4,FALSE) -> 220 | P2: =_xlfn.XLOOKUP(D2,Products_Data!$A:$A,Products_Data!$D:$D) -> 220 | Q2: =H2-(O2*E2) -> 400 | R2: =VLOOKUP(D2,Products_Data!$A:$D,3,FALSE) -> Electronics | S2: =_xlfn.XLOOKUP(D2,Products_Data!$A:$A,Products_Data!$C:$C) -> Electronics | T2: =IF(H2>500,"High","Low") -> High
A3: 1005 | B3: 2025-01-12 | C3: Eitan | D3: P104 | E3: 4 | F3: 200 | G3: North | H3: =E3*F3 -> 800 | J3: South | K3: =SUMIF($G:$G,J3,$H:$H) -> 2380 | L3: =B18/SUM($B$17:$B$20) -> 0.26103647 | M3: =VLOOKUP(D3,Products_Data!$A:$D,2,FALSE) -> Office Chair | N3: =_xlfn.XLOOKUP(D3,Products_Data!$A:$A,Products_Data!$B:$B) -> Office Chair | O3: =VLOOKUP(D3,Products_Data!$A:$D,4,FALSE) -> 150 | P3: =_xlfn.XLOOKUP(D3,Products_Data!$A:$A,Products_Data!$D:$D) -> 150 | Q3: =H3-(O3*E3) -> 200 | R3: =VLOOKUP(D3,Products_Data!$A:$D,3,FALSE) -> Furniture | S3: =_xlfn.XLOOKUP(D3,Products_Data!$A:$A,Products_Data!$C:$C) -> Furniture | T3: =IF(H3>500,"High","Low") -> High
A4: 1007 | B4: 2025-01-18 | C4: Tamar | D4: P105 | E4: 2 | F4: 300 | G4: East | H4: =E4*F4 -> 600 | J4: East | K4: =SUMIF($G:$G,J4,$H:$H) -> 900 | L4: =B19/SUM($B$17:$B$20) -> 0.45681382 | M4: =VLOOKUP(D4,Products_Data!$A:$D,2,FALSE) -> Smartphone | N4: =_xlfn.XLOOKUP(D4,Products_Data!$A:$A,Products_Data!$B:$B) -> Smartphone | O4: =VLOOKUP(D4,Products_Data!$A:$D,4,FALSE) -> 220 | P4: =_xlfn.XLOOKUP(D4,Products_Data!$A:$A,Products_Data!$D:$D) -> 220 | Q4: =H4-(O4*E4) -> 160 | R4: =VLOOKUP(D4,Products_Data!$A:$D,3,FALSE) -> Electronics | S4: =_xlfn.XLOOKUP(D4,Products_Data!$A:$A,Products_Data!$C:$C) -> Electronics | T4: =IF(H4>500,"High","Low") -> High
A5: 1006 | B5: 2025-01-15 | C5: Lior | D5: P102 | E5: 6 | F5: 80 | G5: South | H5: =E5*F5 -> 480 | J5: West | K5: =SUMIF($G:$G,J5,$H:$H) -> 570 | L5: =B20/SUM($B$17:$B$20) -> 0.10940499 | M5: =VLOOKUP(D5,Products_Data!$A:$D,2,FALSE) -> Keyboard | N5: =_xlfn.XLOOKUP(D5,Products_Data!$A:$A,Products_Data!$B:$B) -> Keyboard | O5: =VLOOKUP(D5,Products_Data!$A:$D,4,FALSE) -> 40 | P5: =_xlfn.XLOOKUP(D5,Products_Data!$A:$A,Products_Data!$D:$D) -> 40 | Q5: =H5-(O5*E5) -> 240 | R5: =VLOOKUP(D5,Products_Data!$A:$D,3,FALSE) -> Accessories | S5: =_xlfn.XLOOKUP(D5,Products_Data!$A:$A,Products_Data!$C:$C) -> Accessories | T5: =IF(H5>500,"High","Low") -> Low
A6: 1008 | B6: 2025-01-20 | C6: Omer | D6: P103 | E6: 3 | F6: 150 | G6: West | H6: =E6*F6 -> 450 | M6: =VLOOKUP(D6,Products_Data!$A:$D,2,FALSE) -> Monitor | N6: =_xlfn.XLOOKUP(D6,Products_Data!$A:$A,Products_Data!$B:$B) -> Monitor | O6: =VLOOKUP(D6,Products_Data!$A:$D,4,FALSE) -> 110 | P6: =_xlfn.XLOOKUP(D6,Products_Data!$A:$A,Products_Data!$D:$D) -> 110 | Q6: =H6-(O6*E6) -> 120 | R6: =VLOOKUP(D6,Products_Data!$A:$D,3,FALSE) -> Electronics | S6: =_xlfn.XLOOKUP(D6,Products_Data!$A:$A,Products_Data!$C:$C) -> Electronics | T6: =IF(H6>500,"High","Low") -> Low
A7: 1002 | B7: 2025-01-07 | C7: Maya | D7: P102 | E7: 5 | F7: 80 | G7: South | H7: =E7*F7 -> 400 | M7: =VLOOKUP(D7,Products_Data!$A:$D,2,FALSE) -> Keyboard | N7: =_xlfn.XLOOKUP(D7,Products_Data!$A:$A,Products_Data!$B:$B) -> Keyboard | O7: =VLOOKUP(D7,Products_Data!$A:$D,4,FALSE) -> 40 | P7: =_xlfn.XLOOKUP(D7,Products_Data!$A:$A,Products_Data!$D:$D) -> 40 | Q7: =H7-(O7*E7) -> 200 | R7: =VLOOKUP(D7,Products_Data!$A:$D,3,FALSE) -> Accessories | S7: =_xlfn.XLOOKUP(D7,Products_Data!$A:$A,Products_Data!$C:$C) -> Accessories | T7: =IF(H7>500,"High","Low") -> Low
A8: 1001 | B8: 2025-01-05 | C8: David | D8: P101 | E8: 3 | F8: 120 | G8: North | H8: =E8*F8 -> 360 | M8: =VLOOKUP(D8,Products_Data!$A:$D,2,FALSE) -> Laptop | N8: =_xlfn.XLOOKUP(D8,Products_Data!$A:$A,Products_Data!$B:$B) -> Laptop | O8: =VLOOKUP(D8,Products_Data!$A:$D,4,FALSE) -> 90 | P8: =_xlfn.XLOOKUP(D8,Products_Data!$A:$A,Products_Data!$D:$D) -> 90 | Q8: =H8-(O8*E8) -> 90 | R8: =VLOOKUP(D8,Products_Data!$A:$D,3,FALSE) -> Electronics | S8: =_xlfn.XLOOKUP(D8,Products_Data!$A:$A,Products_Data!$C:$C) -> Electronics | T8: =IF(H8>500,"High","Low") -> Low
A9: 1003 | B9: 2025-01-08 | C9: Noam | D9: P103 | E9: 2 | F9: 150 | G9: East | H9: =E9*F9 -> 300 | M9: =VLOOKUP(D9,Products_Data!$A:$D,2,FALSE) -> Monitor | N9: =_xlfn.XLOOKUP(D9,Products_Data!$A:$A,Products_Data!$B:$B) -> Monitor | O9: =VLOOKUP(D9,Products_Data!$A:$D,4,FALSE) -> 110 | P9: =_xlfn.XLOOKUP(D9,Products_Data!$A:$A,Products_Data!$D:$D) -> 110 | Q9: =H9-(O9*E9) -> 80 | R9: =VLOOKUP(D9,Products_Data!$A:$D,3,FALSE) -> Electronics | S9: =_xlfn.XLOOKUP(D9,Products_Data!$A:$A,Products_Data!$C:$C) -> Electronics | T9: =IF(H9>500,"High","Low") -> Low
A10: 1009 | B10: 2025-01-22 | C10: Roni | D10: P104 | E10: 1 | F10: 200 | G10: North | H10: =E10*F10 -> 200 | M10: =VLOOKUP(D10,Products_Data!$A:$D,2,FALSE) -> Office Chair | N10: =_xlfn.XLOOKUP(D10,Products_Data!$A:$A,Products_Data!$B:$B) -> Office Chair | O10: =VLOOKUP(D10,Products_Data!$A:$D,4,FALSE) -> 150 | P10: =_xlfn.XLOOKUP(D10,Products_Data!$A:$A,Products_Data!$D:$D) -> 150 | Q10: =H10-(O10*E10) -> 50 | R10: =VLOOKUP(D10,Products_Data!$A:$D,3,FALSE) -> Furniture | S10: =_xlfn.XLOOKUP(D10,Products_Data!$A:$A,Products_Data!$C:$C) -> Furniture | T10: =IF(H10>500,"High","Low") -> Low
A11: 1004 | B11: 2025-01-10 | C11: Yael | D11: P101 | E11: 1 | F11: 120 | G11: West | H11: =E11*F11 -> 120 | M11: =VLOOKUP(D11,Products_Data!$A:$D,2,FALSE) -> Laptop | N11: =_xlfn.XLOOKUP(D11,Products_Data!$A:$A,Products_Data!$B:$B) -> Laptop | O11: =VLOOKUP(D11,Products_Data!$A:$D,4,FALSE) -> 90 | P11: =_xlfn.XLOOKUP(D11,Products_Data!$A:$A,Products_Data!$D:$D) -> 90 | Q11: =H11-(O11*E11) -> 30 | R11: =VLOOKUP(D11,Products_Data!$A:$D,3,FALSE) -> Electronics | S11: =_xlfn.XLOOKUP(D11,Products_Data!$A:$A,Products_Data!$C:$C) -> Electronics | T11: =IF(H11>500,"High","Low") -> Low
A16: Region | B16: Total revenue per Region-Sum | D16: Category | E16: Total Revenue per order-Sum | G16: Department | H16: Salary- Average
A17: East | B17: 900 | D17: Accessories | E17: 880 | G17: Finance | H17: 14000
A18: North | B18: 1360 | D18: Electronics | E18: 3330 | G18: HR | H18: 9000
A19: South | B19: 2380 | D19: Furniture | E19: 1000 | G19: IT | H19: 16000
A20: West | B20: 570 | D20: Total | E20: 5210 | G20: Sales | H20: 11500
A21: Total | B21: 5210 | G21: Total | H21: 13000

Sheet Products_Data
A1: Product_ID | B1: Product_Name | C1: Category | D1: Cost_Price | E1: Product Name | F1: Total Revenue per order-Sum | G1: Product Rank
A2: P101 | B2: Laptop | C2: Electronics | D2: 90 | E2: Keyboard | F2: 880 | G2: =RANK(F2,$F$2:$F$6,0) -> 3
A3: P102 | B3: Keyboard | C3: Accessories | D3: 40 | E3: Laptop | F3: 480 | G3: =RANK(F3,$F$2:$F$6,0) -> 5
A4: P103 | B4: Monitor | C4: Electronics | D4: 110 | E4: Monitor | F4: 750 | G4: =RANK(F4,$F$2:$F$6,0) -> 4
A5: P104 | B5: Office Chair | C5: Furniture | D5: 150 | E5: Office Chair | F5: 1000 | G5: =RANK(F5,$F$2:$F$6,0) -> 2
A6: P105 | B6: Smartphone | C6: Electronics | D6: 220 | E6: Smartphone | F6: 2100 | G6: =RANK(F6,$F$2:$F$6,0) -> 1
E7: Total | F7: 5210

Sheet Employees_Data
A1: Employee_ID | B1: Employee_Name | C1: Department | D1: Salary | E1: Bonus | F1: Average Salary | G1: Department | H1: Number of employees per department
A2: 1 | B2: Daniel | C2: Sales | D2: 12000 | E2: 1500 | F2: =AVERAGE(D2:D7) -> 13000 | G2: IT | H2: =COUNTIF($C:$C,G2) -> 2
A3: 2 | B3: Leah | C3: IT | D3: 15000 | E3: 2000 | G3: Sales | H3: =COUNTIF($C:$C,G3) -> 2
A4: 3 | B4: Yossi | C4: Sales | D4: 11000 | E4: 1200 | G4: HR | H4: =COUNTIF($C:$C,G4) -> 1
A5: 4 | B5: Michal | C5: HR | D5: 9000 | E5: 800 | G5: Finance | H5: =COUNTIF($C:$C,G5) -> 1
A6: 5 | B6: Avi | C6: IT | D6: 17000 | E6: 2500
A7: 6 | B7: Dana | C7: Finance | D7: 14000 | E7: 1800
